weaver/exceptions.py
weaver/building_blocks/__init__.py
weaver/building_blocks/tools.py
weaver/core/__init__.py
weaver/core/chains.py
weaver/core/graph.py
weaver/models/__init__.py
weaver/models/actions.py
weaver/models/events.py
weaver/models/state.py
weaver/runtime/__init__.py
weaver/runtime/coordinator.py
weaver/runtime/policy.py
weaver/runtime/runtime.py
weaver_ai-0.0.1.dist-info/licenses/LICENSE
weaver_ai-0.0.1.dist-info/METADATA
weaver_ai-0.0.1.dist-info/WHEEL
weaver_ai-0.0.1.dist-info/top_level.txt
weaver_ai-0.0.1.dist-info/RECORD
