Metadata-Version: 2.4
Name: weaver-ai
Version: 0.0.1
Summary: A native framework for building collaborative AI.
Author: REN Yifan
License-Expression: Apache-2.0
Project-URL: Homepage, https://github.com/fanrenaz/Weaver
Project-URL: Documentation, https://github.com/fanrenaz/Weaver#readme
Project-URL: Source, https://github.com/fanrenaz/Weaver
Project-URL: Issues, https://github.com/fanrenaz/Weaver/issues
Keywords: agents,ai,collaboration,mediation,langchain,framework
Classifier: Development Status :: 2 - Pre-Alpha
Classifier: Intended Audience :: Developers
Classifier: Programming Language :: Python :: 3
Classifier: Programming Language :: Python :: 3.12
Classifier: Topic :: Scientific/Engineering :: Artificial Intelligence
Classifier: Topic :: Software Development :: Libraries
Requires-Python: >=3.12
License-File: LICENSE
Requires-Dist: langchain
Requires-Dist: langgraph
Requires-Dist: langchain-openai
Requires-Dist: pydantic
Requires-Dist: python-dotenv
Requires-Dist: langchain-community
Provides-Extra: dev
Requires-Dist: pytest; extra == "dev"
Requires-Dist: ruff; extra == "dev"
Requires-Dist: black; extra == "dev"
Requires-Dist: ipykernel; extra == "dev"
Requires-Dist: mkdocs; extra == "dev"
Requires-Dist: mkdocs-material; extra == "dev"
Requires-Dist: mkdocstrings[python]; extra == "dev"
Requires-Dist: mkdocs-gen-files; extra == "dev"
Requires-Dist: mkdocs-literate-nav; extra == "dev"
Dynamic: license-file
